{
  "name": "Campaña: Inicio Mes de Cumpleaños",
  "nodes": [
    {
      "parameters": {
        "rule": {
          "type": "cron",
          "value": "0 9 1 * *"
        }
      },
      "id": "trigger-inicio-mes",
      "name": "Cron (Día 1 del Mes)",
      "type": "n8n-nodes-base.scheduleTrigger",
      "typeVersion": 1.2,
      "position": [
        0,
        0
      ]
    },
    {
      "parameters": {
        "operation": "getAll",
        "tableId": "clientes_fidelizacion",
        "returnAll": true
      },
      "id": "supabase-buscar-clientes",
      "name": "Supabase: Buscar Clientes",
      "type": "n8n-nodes-base.supabase",
      "typeVersion": 1,
      "position": [
        200,
        0
      ],
      "credentials": {
        "supabaseApi": {
          "id": "5hkYuZVAhznvx7lf",
          "name": "Supabase Fidelizacion Narbo's Pro"
        }
      }
    },
    {
      "parameters": {
        "conditions": {
          "options": {
            "caseSensitive": true,
            "leftValue": "",
            "typeValidation": "strict",
            "version": 3
          },
          "conditions": [
            {
              "id": "cond-mes",
              "leftValue": "={{ $json.birthday ? $json.birthday.substring(5, 7) : '00' }}",
              "rightValue": "={{ $now.toFormat('MM') }}",
              "operator": {
                "type": "string",
                "operation": "equals"
              }
            }
          ],
          "combinator": "and"
        },
        "options": {}
      },
      "id": "filter-mes-cumpleanos",
      "name": "Filtrar: Cumplen este Mes",
      "type": "n8n-nodes-base.filter",
      "typeVersion": 2.3,
      "position": [
        400,
        0
      ]
    },
    {
      "parameters": {
        "tableId": "bonos",
        "fieldsUi": {
          "fieldValues": [
            {
              "fieldId": "client_id",
              "fieldValue": "={{ $json[\"id\"].trim() }}"
            },
            {
              "fieldId": "tipo",
              "fieldValue": "Cumpleaños"
            },
            {
              "fieldId": "estado",
              "fieldValue": "Pendiente"
            },
            {
              "fieldId": "codigo",
              "fieldValue": "=NARBO-HB{{ $now.toFormat('yyyy') }}-{{ Math.random().toString(36).substring(2,6).toUpperCase() }}"
            },
            {
              "fieldId": "user_id",
              "fieldValue": "={{ $json[\"user_id\"] }}"
            },
            {
              "fieldId": "tenant_id",
              "fieldValue": "={{ $json[\"tenant_id\"] || $json[\"user_id\"] }}"
            }
          ]
        }
      },
      "id": "supabase-guardar-bono",
      "name": "Supabase: Guardar Bono (Mensual)",
      "type": "n8n-nodes-base.supabase",
      "typeVersion": 1,
      "position": [
        600,
        0
      ],
      "credentials": {
        "supabaseApi": {
          "id": "5hkYuZVAhznvx7lf",
          "name": "Supabase Fidelizacion Narbo's Pro"
        }
      }
    },
    {
      "parameters": {
        "fromEmail": "contacto@narbossalon.com",
        "toEmail": "={{ $('Filtrar: Cumplen este Mes').item.json.email }}",
        "subject": "¡Empieza tu mes de cumpleaños! 🎁 Descuento especial de Narbo's",
        "emailFormat": "html",
        "html": "==<!DOCTYPE html>\n<html lang=\"es\">\n<head>\n    <meta charset=\"UTF-8\">\n    <meta name=\"viewport\" content=\"width=device-width, initial-scale=1.0\">\n</head>\n<body style=\"margin: 0; padding: 0; font-family: 'Montserrat', sans-serif; background-color: #f7f7f7;\">\n    <div style=\"max-width: 600px; margin: 40px auto; background-color: #ffffff; border-radius: 12px; overflow: hidden; box-shadow: 0 4px 15px rgba(0,0,0,0.05);\">\n        <div style=\"background-color: #6B755A; padding: 40px 20px; text-align: center;\">\n            <img src=\"https://narbossalon.com/images/brand/logo_narbos.png\" alt=\"Narbo's Salón\" width=\"200\" style=\"height: auto; max-width: 200px; margin-bottom: 20px;\">\n            <h1 style=\"font-family: 'Playfair Display', serif; color: #ffffff; margin: 0; font-size: 24px;\">¡Bienvenido a tu mes de Cumpleaños! 🎂</h1>\n        </div>\n        <div style=\"padding: 40px 30px; text-align: center;\">\n            <p style=\"font-size: 16px; line-height: 1.6; color: #666666; margin-bottom: 30px;\">\n                Hola <b>{{ $('Filtrar: Cumplen este Mes').item.json[\"nombre\"] }}</b>,<br><br>\n                En Narbo's Salón Spa nos encanta celebrar contigo, y qué mejor forma de hacerlo que dándote todo el mes para disfrutar de tu regalo.\n            </p>\n            <div style=\"background-color: #f9f9f9; padding: 25px; border-radius: 20px; border: 2px solid #6B755A; display: inline-block; margin-bottom: 30px;\">\n                <p style=\"margin: 0; font-size: 14px; color: #888888; text-transform: uppercase;\">🎁 Bono de 15% de descuento</p>\n                <p style=\"margin: 10px 0 0 0; font-size: 18px; font-weight: 600; color: #5B4636;\">Código: {{ $json[\"codigo\"] }}</p>\n                <div style=\"margin-top: 15px; text-align: center;\">\n                    <div style=\"display: inline-block; padding: 15px; background-color: #ffffff; border: 1px solid #eeeeee; border-radius: 12px; box-shadow: 0 4px 10px rgba(0,0,0,0.05);\">\n                        <img src=\"https://api.qrserver.com/v1/create-qr-code/?data={{ encodeURIComponent('https://n8n.srv1033442.hstgr.cloud/webhook/canje-QR?code=' + $json['codigo']) }}&size=200x200&format=png&bgcolor=ffffff&qzone=1\" alt=\"Código QR de tu Bono\" width=\"200\" height=\"200\" style=\"display: block; border: 0; outline: none; text-decoration: none;\">\n                    </div>\n                    <p style=\"font-size: 13px; color: #999999; margin-top: 10px;\">Escanea este código en el salón</p>\n                </div>\n            </div>\n            <p style=\"font-size: 14px; color: #999999; margin-bottom: 30px;\">Tienes hasta el <b>último día de este mes</b> para agendar y usar tu bono. ¡No lo dejes pasar!</p>\n            <a href=\"https://wa.me/573123462618?text=Hola%20Narbo's!%20Inici%C3%B3%20mi%20mes%20de%20cumplea%C3%B1os%20y%20me%20gustar%C3%ADa%20reservar%20mi%20cita%20con%20el%20bono.\" style=\"display: inline-block; background-color: #6B755A; color: #ffffff; text-decoration: none; padding: 14px 28px; border-radius: 30px; font-weight: 600;\">Agendar mi Cita</a>\n        </div>\n        <div style=\"background-color: #333333; color: #ffffff; padding: 20px; text-align: center; font-size: 11px;\">\n            <p><strong>*Condiciones:</strong> Válido para 1 solo uso durante el mes en curso. No acumulable con otras promociones.</p>\n            <p style=\"margin-top: 5px;\">© 2026 Narbo's Salón Spa &bull; Chía, Cundinamarca.</p>\n        </div>\n    </div>\n</body>\n</html>\n",
        "options": {}
      },
      "id": "email-inicio-mes",
      "name": "Email: Enviar Bono Mes",
      "type": "n8n-nodes-base.emailSend",
      "typeVersion": 2,
      "position": [
        800,
        0
      ],
      "credentials": {
        "smtp": {
          "id": "lHxckxi50jQr6fuv",
          "name": "Correo: contacto@narbossalon.com"
        }
      }
    },
    {
      "parameters": {
        "content": "## 📅 Campaña: Mes de Cumpleaños\n1. Se ejecuta el día 1 de cada mes a las 9:00 AM.\n2. Busca a todos los clientes que cumplan en el mes actual.\n3. Les genera el bono desde el primer día.\n4. Envía correo QR dándoles todo el mes para redimirlo.",
        "height": 221,
        "width": 1058,
        "color": 2
      },
      "id": "sticky-mes-cumple",
      "name": "Sticky Note",
      "type": "n8n-nodes-base.stickyNote",
      "typeVersion": 1,
      "position": [
        -20,
        -260
      ]
    }
  ],
  "pinData": {},
  "connections": {
    "Cron (Día 1 del Mes)": {
      "main": [
        [
          {
            "node": "Supabase: Buscar Clientes",
            "type": "main",
            "index": 0
          }
        ]
      ]
    },
    "Supabase: Buscar Clientes": {
      "main": [
        [
          {
            "node": "Filtrar: Cumplen este Mes",
            "type": "main",
            "index": 0
          }
        ]
      ]
    },
    "Filtrar: Cumplen este Mes": {
      "main": [
        [
          {
            "node": "Supabase: Guardar Bono (Mensual)",
            "type": "main",
            "index": 0
          }
        ]
      ]
    },
    "Supabase: Guardar Bono (Mensual)": {
      "main": [
        [
          {
            "node": "Email: Enviar Bono Mes",
            "type": "main",
            "index": 0
          }
        ]
      ]
    }
  },
  "settings": {
    "executionOrder": "v1"
  }
}
